georecl/__init__.py
georecl/geoserver.py
georecl/main.py
georecl-0.1.1.dist-info/METADATA
georecl-0.1.1.dist-info/WHEEL
georecl-0.1.1.dist-info/RECORD
