Metadata-Version: 2.1
Name: georecl
Version: 0.1.1
Summary: A geoserver rest client supporting authkey and basic auth(user,pass)
Author: Mukesh
Author-email: mkpandey.irs@gmail.com
Requires-Python: >=3.12,<4.0
Classifier: Programming Language :: Python :: 3
Classifier: Programming Language :: Python :: 3.12
Requires-Dist: requests (>=2.32.2,<3.0.0)
